orpheus/__init__.py
orpheus/components.py
orpheus/config.py
orpheus/model.py
orpheus/utils.py
orpheus/train/components.py
orpheus/train/stage_1.py
orpheus/train/utils.py
canopy_orpheus-0.0.19.dist-info/METADATA
canopy_orpheus-0.0.19.dist-info/WHEEL
canopy_orpheus-0.0.19.dist-info/top_level.txt
canopy_orpheus-0.0.19.dist-info/RECORD
