Metadata-Version: 2.2
Name: canopy-orpheus
Version: 0.0.19
Summary: A small example package
Author-email: Canopy Labs <amu@canopylabs.ai>
License: MIT
Project-URL: Homepage, https://github.com/pypa/sampleproject
Project-URL: Issues, https://github.com/pypa/sampleproject/issues
Classifier: Programming Language :: Python :: 3
Classifier: Operating System :: OS Independent
Requires-Python: >=3.8
Requires-Dist: torch==2.5.1
Requires-Dist: transformers
Requires-Dist: torchaudio
Requires-Dist: librosa
Requires-Dist: soundfile
Requires-Dist: snac
Requires-Dist: openai-whisper
Requires-Dist: trl
Requires-Dist: datasets
